setup.py
pyjuxa/__init__.py
pyjuxa.egg-info/PKG-INFO
pyjuxa.egg-info/SOURCES.txt
pyjuxa.egg-info/dependency_links.txt
pyjuxa.egg-info/not-zip-safe
pyjuxa.egg-info/top_level.txt