Metadata-Version: 1.0
Name: pyjuxa
Version: 0.0.1
Summary: python JUnit Xml Analyzer
Home-page: http://github.com/renemilk/pyjuxa
Author: René Milk
Author-email: rene@milk.pm
License: BSD-2
Platform: UNKNOWN
